wows_shell.cp39-win_amd64.pyd
wows_shell-1.2.3.dist-info/LICENSE
wows_shell-1.2.3.dist-info/METADATA
wows_shell-1.2.3.dist-info/WHEEL
wows_shell-1.2.3.dist-info/top_level.txt
wows_shell-1.2.3.dist-info/RECORD
