Metadata-Version: 2.1
Name: wows-shell
Version: 1.2.3
Summary: Python extension of wows_shell
Home-page: https://github.com/jcw780/wows_shell
License: UNKNOWN
Platform: UNKNOWN
License-File: LICENSE
